pydiverse/colspec/__init__.py
pydiverse/colspec/_filter.py
pydiverse/colspec/_rule.py
pydiverse/colspec/_validation.py
pydiverse/colspec/collection.py
pydiverse/colspec/colspec.py
pydiverse/colspec/config.py
pydiverse/colspec/exc.py
pydiverse/colspec/failure.py
pydiverse/colspec/optional_dependency.py
pydiverse/colspec/pdt_util.py
pydiverse/colspec/py.typed
pydiverse/colspec/version.py
pydiverse/colspec/columns/__init__.py
pydiverse/colspec/columns/_base.py
pydiverse/colspec/columns/_mixins.py
pydiverse/colspec/columns/_utils.py
pydiverse/colspec/columns/any.py
pydiverse/colspec/columns/bool.py
pydiverse/colspec/columns/datetime.py
pydiverse/colspec/columns/decimal.py
pydiverse/colspec/columns/enum.py
pydiverse/colspec/columns/float.py
pydiverse/colspec/columns/integer.py
pydiverse/colspec/columns/list.py
pydiverse/colspec/columns/string.py
pydiverse/colspec/columns/struct.py
pydiverse/colspec/testing/__init__.py
pydiverse/colspec/testing/assert_equal.py
pydiverse/colspec/testing/const.py
pydiverse/colspec/testing/factory.py
pydiverse/colspec/testing/rules.py
pydiverse/colspec/testing/typing.py
pydiverse_colspec-0.3.1.dist-info/METADATA
pydiverse_colspec-0.3.1.dist-info/WHEEL
pydiverse_colspec-0.3.1.dist-info/licenses/LICENSE
pydiverse_colspec-0.3.1.dist-info/RECORD
