Metadata-Version: 2.4
Name: pydiverse-colspec
Version: 0.3.1
Summary: Validate column specifications and constraints for SQL tables and polars data frames.
Author: QuantCo, Inc.
Author-email: Martin Trautmann <windiana@users.sf.net>, Finn Rudolph <finn.rudolph@t-online.de>
License: BSD 3-Clause License
License-File: LICENSE
Classifier: Development Status :: 4 - Beta
Classifier: Intended Audience :: Developers
Classifier: Intended Audience :: Science/Research
Classifier: License :: OSI Approved :: BSD License
Classifier: Programming Language :: Python :: 3
Classifier: Programming Language :: Python :: 3.11
Classifier: Programming Language :: Python :: 3.12
Classifier: Programming Language :: Python :: 3.13
Classifier: Programming Language :: Python :: 3.14
Classifier: Programming Language :: SQL
Classifier: Topic :: Database
Classifier: Topic :: Scientific/Engineering
Classifier: Topic :: Software Development
Requires-Python: <3.15,>=3.11
Requires-Dist: pydiverse-common<0.5,>=0.4.0
Requires-Dist: structlog<26,>=25.4.0
